ds_reify/__init__.py
ds_reify/commands/hello.py
ds_reify/dsreify.py
ds_reify/styles.py
ds_reify-0.1.0.dist-info/LICENSE
ds_reify-0.1.0.dist-info/METADATA
ds_reify-0.1.0.dist-info/WHEEL
ds_reify-0.1.0.dist-info/entry_points.txt
ds_reify-0.1.0.dist-info/RECORD
