Metadata-Version: 2.1
Name: ds-reify
Version: 0.1.0
Summary: A CLI helper for [Distributed-Something](https://github.com/DistributedScience/Distributed-Something)
Home-page: https://distributedscience.github.io/Distributed-Something/introduction.html
License: MIT
Keywords: Distributed-Something,DistributedScience
Author: Nodar Gogoberidze
Author-email: gnodar01@gmail.com
Requires-Python: >=3.8.1,<4.0.0
Classifier: License :: OSI Approved :: MIT License
Classifier: Programming Language :: Python :: 3
Classifier: Programming Language :: Python :: 3.9
Classifier: Programming Language :: Python :: 3.10
Classifier: Programming Language :: Python :: 3.11
Requires-Dist: rich-click (>=1.6.1,<2.0.0)
Project-URL: Repository, https://github.com/gnodar01/ds-reify
